COPYING
MANIFEST.in
README.rst
bootstrap-buildout.py
buildout.cfg
requirements.txt
setup.py
version.txt
doc/conf.py
doc/index.rst
xspear/__init__.py
xspear.btas2015.egg-info/PKG-INFO
xspear.btas2015.egg-info/SOURCES.txt
xspear.btas2015.egg-info/dependency_links.txt
xspear.btas2015.egg-info/entry_points.txt
xspear.btas2015.egg-info/not-zip-safe
xspear.btas2015.egg-info/requires.txt
xspear.btas2015.egg-info/top_level.txt
xspear/btas2015/__init__.py
xspear/btas2015/config/__init__.py
xspear/btas2015/config/algorithm/__init__.py
xspear/btas2015/config/algorithm/isv_avspoof.py
xspear/btas2015/config/algorithm/ivec_avspoof.py
xspear/btas2015/config/database/__init__.py
xspear/btas2015/config/database/avspoof.py
xspear/btas2015/script/__init__.py
xspear/btas2015/script/evaluate_vulnerability.py