Metadata-Version: 1.1
Name: xspear.btas2015
Version: 2.0.1a0
Summary: On the Vulnerability of Speaker Verification to Realistic Voice Spoofing
Home-page: https://pypi.python.org/pypi/spear.btas2015
Author: Elie Khoury
Author-email: Elie.Khoury@idiap.ch
License: GPLv3
Keywords: Speaker verification,Spoofing,Vulnerability,Database
Platform: UNKNOWN
Classifier: Development Status :: 4 - Beta
Classifier: Intended Audience :: Developers
Classifier: License :: OSI Approved :: GNU General Public License v3 (GPLv3)
Classifier: Natural Language :: English
Classifier: Programming Language :: Python
Classifier: Topic :: Scientific/Engineering :: Artificial Intelligence
